storageCat/__init__.py
storageCat/classes.py
storageCat/cli.py
storagecat-1.0.2.dist-info/licenses/LICENSE
storagecat-1.0.2.dist-info/METADATA
storagecat-1.0.2.dist-info/WHEEL
storagecat-1.0.2.dist-info/entry_points.txt
storagecat-1.0.2.dist-info/top_level.txt
storagecat-1.0.2.dist-info/RECORD
